LICENSE.txt
MANIFEST.in
README.txt
setup.py
Ygrep.egg-info/PKG-INFO
Ygrep.egg-info/SOURCES.txt
Ygrep.egg-info/dependency_links.txt
Ygrep.egg-info/entry_points.txt
Ygrep.egg-info/top_level.txt
ygrep/__init__.py
ygrep/serializer.py
ygrep/util.py
ygrep/ygreplib.py
ygrep/ygrepmain.py
ygrep/tests/__init__.py
ygrep/tests/ygreptest.py