Metadata-Version: 1.1
Name: Ygrep
Version: 0.1dev
Summary: UNKNOWN
Home-page: https://github.com/marianobarrios/ygrep
Author: Mariano Barrios
Author-email: marianobarrios@gmail.com
License: GPL
Platform: UNKNOWN
Requires: P
Requires: y
Requires: Y
Requires: A
Requires: M
Requires: L
